monitorBuildingDash/build_configuration_files_devices.py
monitorBuildingDash/screenBuilding.py
monitorBuildingDash/screenBuildingTabs.py
monitorBuildingDash/confFiles/ALSTOM_MODBUS_MBA_SYLFEN_V2.xlsx
monitorBuildingDash/confFiles/build_df_gtc_alstom.py
monitorBuildingDash/confFiles/devices_monitoring_v1.ods
monitorBuildingDash/confFiles/gtc_alstom_modebus_map.pkl
monitorBuildingDash/confFiles/gtc_alstom_plc.pkl
monitorBuildingDash/confFiles/monitorbuilding_configfiles.ods
monitorBuildingDash/confFiles/screeningBuilding_user.md
monitorBuildingDash/confFiles/site_sls_modebus_map.pkl
monitorBuildingDash/confFiles/site_sls_plc.pkl
monitorBuildingDash/confFiles/smartlogger_modebus_map.pkl
monitorBuildingDash/confFiles/smartlogger_plc.pkl
monitorBuildingDash/confFiles/vmuc_ModbusTCP_Map_2022_01_10.xml
monitorBuildingDash/confFiles/vmuc_modebus_map.pkl
monitorBuildingDash/confFiles/vmuc_plc.pkl
monitorBuildingDash/confFiles/PLC_config/alldfsPLC.pkl
monitorBuildingDash/confFiles/PLC_config/map_missingTags.pkl
monitorBuildingDash/confFiles/PLC_config/map_presenceTags.pkl
monitorBuildingDash/confFiles/PLC_config/nbTags.pkl
monitorBuildingDash/confFiles/PLC_config/plc_v0.1.csv
monitorBuildingDash/confFiles/PLC_config/plc_v0.2.csv
monitorBuildingDash/confFiles/PLC_config/plc_v1.0.csv
monitorBuildingDash/confFiles/PLC_config/versionnageTags.ods
monitorBuildingDash/confFiles/new/ALSTOM_MODBUS_MBA_SYLFEN.xlsx
monitorBuildingDash/confFiles/new/ModbusTCP_Map_2022_03_15.xml
monitorBuildingDash/old/configFilesBuilding.py
monitorBuildingDash-4.3.2.dist-info/METADATA
monitorBuildingDash-4.3.2.dist-info/WHEEL
monitorBuildingDash-4.3.2.dist-info/top_level.txt
monitorBuildingDash-4.3.2.dist-info/RECORD
